{
    "boxShadow": "none",
    "widgetName": "Container1",
    "borderColor": "transparent",
    "disallowCopy": true,
    "isCanvas": true,
    "dynamicPropertyPathList": [{"key": "borderRadius"}],
    "displayName": "Container",
    "iconSVG": "/static/media/icon.1977dca3.svg",
    "topRow": 0,
    "bottomRow": 27,
    "dragDisabled": true,
    "type": "CONTAINER_WIDGET",
    "hideCard": false,
    "openParentPropertyPane": true,
    "isDeletable": false,
    "animateLoading": true,
    "leftColumn": 0,
    "dynamicBindingPathList": [],
    "children": [{
        "labelTextSize": "0.875rem",
        "boxShadow": "none",
        "widgetName": "Canvas5",
        "detachFromLayout": true,
        "displayName": "Canvas",
        "widgetId": "whobv65m8v",
        "topRow": 0,
        "bottomRow": 260,
        "containerStyle": "none",
        "parentRowSpace": 1,
        "isVisible": true,
        "type": "CANVAS_WIDGET",
        "canExtend": false,
        "version": 1,
        "hideCard": true,
        "parentId": "nyzottzh9b",
        "renderMode": "CANVAS",
        "isLoading": false,
        "parentColumnSpace": 1,
        "leftColumn": 0,
        "dynamicBindingPathList": [],
        "borderRadius": "0px",
        "key": "jl43dpihp4"
    }],
    "borderWidth": "0",
    "key": "a41w0zi2br",
    "disablePropertyPane": true,
    "labelTextSize": "0.875rem",
    "backgroundColor": "white",
    "rightColumn": 64,
    "dynamicHeight": "FIXED",
    "widgetId": "nyzottzh9b",
    "containerStyle": "card",
    "isVisible": true,
    "version": 1,
    "parentId": "6s0e0r3hdg",
    "renderMode": "CANVAS",
    "isLoading": false,
    "borderRadius": "0px",
    "maxDynamicHeight": 9000,
    "minDynamicHeight": 4
}